MANIFEST.in
account_check_writing_data.xml
account_check_writing_report.xml
account_demo.xml
account_view.xml
account_voucher_view.xml
setup.py
./__init__.py
./__openerp__.py
./account.py
./account_voucher.py
./report/__init__.py
./report/check_print.py
./wizard/__init__.py
./wizard/account_check_batch_printing.py
i18n/account_check_writing.pot
i18n/ar.po
i18n/bs.po
i18n/cs.po
i18n/de.po
i18n/en_GB.po
i18n/es.po
i18n/es_CR.po
i18n/es_EC.po
i18n/es_MX.po
i18n/fi.po
i18n/fr.po
i18n/gu.po
i18n/hr.po
i18n/hu.po
i18n/ja.po
i18n/lt.po
i18n/mk.po
i18n/mn.po
i18n/nb.po
i18n/nl.po
i18n/pl.po
i18n/pt.po
i18n/pt_BR.po
i18n/ro.po
i18n/ru.po
i18n/sl.po
i18n/sr@latin.po
i18n/sv.po
i18n/tr.po
i18n/zh_CN.po
i18n/zh_TW.po
openerp_account_check_writing.egg-info/PKG-INFO
openerp_account_check_writing.egg-info/SOURCES.txt
openerp_account_check_writing.egg-info/dependency_links.txt
openerp_account_check_writing.egg-info/requires.txt
openerp_account_check_writing.egg-info/top_level.txt
report/check_print.sxw
report/check_print_bottom.rml
report/check_print_bottom.sxw
report/check_print_middle.rml
report/check_print_middle.sxw
report/check_print_top.rml
report/check_print_top.sxw
wizard/account_check_batch_printing_view.xml